[
    {
        "fields": {
            "base_app.city.name": "Самоков",
            "name": "Професионална Гимназия по Туризъм"
        },
        "model": "base_app.school"
    },
    {
        "fields": {
            "base_app.city.name": "Самоков",
            "name": "Профилирана Гимназия Константин Фотинов"
        },
        "model": "base_app.school"
    },
    {
        "fields": {
            "base_app.city.name": "Самоков",
            "name": "Професионална Техническа Гимназия Никола Й. Вапцаров"
        },
        "model": "base_app.school"
    },
    {
        "fields": {
            "base_app.city.name": "Самоков",
            "name": "Средно Общообразователно Училище Отец Паисий"
        },
        "model": "base_app.school"
    }
]